odoo/addons/hr_personal_equipment_variant_configurator/README.rst
odoo/addons/hr_personal_equipment_variant_configurator/__init__.py
odoo/addons/hr_personal_equipment_variant_configurator/__manifest__.py
odoo/addons/hr_personal_equipment_variant_configurator/i18n/es.po
odoo/addons/hr_personal_equipment_variant_configurator/i18n/es_PA.po
odoo/addons/hr_personal_equipment_variant_configurator/i18n/hr_personal_equipment_variant_configurator.pot
odoo/addons/hr_personal_equipment_variant_configurator/i18n/it.po
odoo/addons/hr_personal_equipment_variant_configurator/i18n/pt_BR.po
odoo/addons/hr_personal_equipment_variant_configurator/models/__init__.py
odoo/addons/hr_personal_equipment_variant_configurator/models/hr_personal_equipment.py
odoo/addons/hr_personal_equipment_variant_configurator/readme/CONTRIBUTORS.rst
odoo/addons/hr_personal_equipment_variant_configurator/readme/DESCRIPTION.rst
odoo/addons/hr_personal_equipment_variant_configurator/readme/INSTALL.rst
odoo/addons/hr_personal_equipment_variant_configurator/static/description/icon.png
odoo/addons/hr_personal_equipment_variant_configurator/static/description/index.html
odoo/addons/hr_personal_equipment_variant_configurator/views/hr_personal_equipment_request.xml
odoo14_addon_hr_personal_equipment_variant_configurator-14.0.1.0.1.dev13.dist-info/METADATA
odoo14_addon_hr_personal_equipment_variant_configurator-14.0.1.0.1.dev13.dist-info/WHEEL
odoo14_addon_hr_personal_equipment_variant_configurator-14.0.1.0.1.dev13.dist-info/top_level.txt
odoo14_addon_hr_personal_equipment_variant_configurator-14.0.1.0.1.dev13.dist-info/RECORD
